{
  "DLSVersion": "2.1.6",
  "Name": "AND-4",
  "NameLocation": 0,
  "ChipType": 0,
  "Size": {
    "x": 0.875,
    "y": 1.0
  },
  "Colour": {
    "r": 0.113759518,
    "g": 0.0135814771,
    "b": 0.764080048,
    "a": 1
  },
  "InputPins":[
    {
      "Name":"IN",
      "ID":1690467366,
      "Position":{
        "x":-5.31183,
        "y":0.94524
      },
      "BitCount":1,
      "Colour":0,
      "ValueDisplayMode":0
    },
    {
      "Name":"IN",
      "ID":2090819378,
      "Position":{
        "x":-5.31183,
        "y":0.43024
      },
      "BitCount":1,
      "Colour":0,
      "ValueDisplayMode":0
    },
    {
      "Name":"IN",
      "ID":133624384,
      "Position":{
        "x":-5.31183,
        "y":-0.08476
      },
      "BitCount":1,
      "Colour":0,
      "ValueDisplayMode":0
    },
    {
      "Name":"IN",
      "ID":858977689,
      "Position":{
        "x":-5.31183,
        "y":-0.59976
      },
      "BitCount":1,
      "Colour":0,
      "ValueDisplayMode":0
    }
  ],
  "OutputPins":[
    {
      "Name":"OUT",
      "ID":361196553,
      "Position":{
        "x":1.01042,
        "y":-0.16393
      },
      "BitCount":1,
      "Colour":0,
      "ValueDisplayMode":0
    }
  ],
  "SubChips":[
    {
      "Name":"AND-3",
      "ID":207413001,
      "Label":"",
      "Position":{
        "x":-2.57589,
        "y":0.72341
      },
      "OutputPinColourInfo":[{"PinColour":0,"PinID":854899745}],
      "InternalData":null
    },
    {
      "Name":"AND",
      "ID":362244936,
      "Label":"",
      "Position":{
        "x":-1.097,
        "y":-0.17625
      },
      "OutputPinColourInfo":[{"PinColour":0,"PinID":2062905707}],
      "InternalData":null
    }
  ],
  "Wires":[
    {
      "SourcePinAddress":{
        "PinID":0,
        "PinOwnerID":1690467366
      },
      "TargetPinAddress":{
        "PinID":2132774254,
        "PinOwnerID":207413001
      },
      "ConnectionType":0,
      "ConnectedWireIndex":-1,
      "ConnectedWireSegmentIndex":-1,
      "Points":[{"x":0.0,"y":0.0},{"x":0.0,"y":0.0}]
    },
    {
      "SourcePinAddress":{
        "PinID":0,
        "PinOwnerID":2090819378
      },
      "TargetPinAddress":{
        "PinID":1708245147,
        "PinOwnerID":207413001
      },
      "ConnectionType":0,
      "ConnectedWireIndex":-1,
      "ConnectedWireSegmentIndex":-1,
      "Points":[{"x":0.0,"y":0.0},{"x":0.0,"y":0.0}]
    },
    {
      "SourcePinAddress":{
        "PinID":0,
        "PinOwnerID":133624384
      },
      "TargetPinAddress":{
        "PinID":465147624,
        "PinOwnerID":207413001
      },
      "ConnectionType":0,
      "ConnectedWireIndex":-1,
      "ConnectedWireSegmentIndex":-1,
      "Points":[{"x":0.0,"y":0.0},{"x":0.0,"y":0.0}]
    },
    {
      "SourcePinAddress":{
        "PinID":0,
        "PinOwnerID":858977689
      },
      "TargetPinAddress":{
        "PinID":1269493727,
        "PinOwnerID":362244936
      },
      "ConnectionType":0,
      "ConnectedWireIndex":-1,
      "ConnectedWireSegmentIndex":-1,
      "Points":[{"x":0.0,"y":0.0},{"x":0.0,"y":0.0}]
    },
    {
      "SourcePinAddress":{
        "PinID":854899745,
        "PinOwnerID":207413001
      },
      "TargetPinAddress":{
        "PinID":1227132613,
        "PinOwnerID":362244936
      },
      "ConnectionType":0,
      "ConnectedWireIndex":-1,
      "ConnectedWireSegmentIndex":-1,
      "Points":[{"x":0.0,"y":0.0},{"x":0.0,"y":0.0}]
    },
    {
      "SourcePinAddress":{
        "PinID":2062905707,
        "PinOwnerID":362244936
      },
      "TargetPinAddress":{
        "PinID":0,
        "PinOwnerID":361196553
      },
      "ConnectionType":0,
      "ConnectedWireIndex":-1,
      "ConnectedWireSegmentIndex":-1,
      "Points":[{"x":0.0,"y":0.0},{"x":0.0,"y":0.0}]
    }
  ],
  "Displays": null
}