{
  "Name": "MUX",
  "NameLocation": 0,
  "ChipType": 0,
  "Size": {
    "x": 1.325,
    "y": 2.75
  },
  "Colour": {
    "r": 0.8262018,
    "g": 0.649097145,
    "b": 0.958248734,
    "a": 1
  },
  "InputPins":[
    {
      "Name":"C1",
      "ID":1584892759,
      "Position":{
        "x":-28.38937,
        "y":8.01462
      },
      "BitCount":1,
      "Colour":3,
      "ValueDisplayMode":0
    },
    {
      "Name":"C2",
      "ID":2138233393,
      "Position":{
        "x":-28.40738,
        "y":6.70739
      },
      "BitCount":1,
      "Colour":4,
      "ValueDisplayMode":0
    },
    {
      "Name":"C4",
      "ID":509777400,
      "Position":{
        "x":-28.42539,
        "y":5.30591
      },
      "BitCount":1,
      "Colour":5,
      "ValueDisplayMode":0
    },
    {
      "Name":"0",
      "ID":1967958892,
      "Position":{
        "x":-30.51437,
        "y":4.45212
      },
      "BitCount":1,
      "Colour":6,
      "ValueDisplayMode":0
    },
    {
      "Name":"1",
      "ID":1672132232,
      "Position":{
        "x":-30.51437,
        "y":3.32712
      },
      "BitCount":1,
      "Colour":1,
      "ValueDisplayMode":0
    },
    {
      "Name":"2",
      "ID":1176604405,
      "Position":{
        "x":-30.51437,
        "y":2.20212
      },
      "BitCount":1,
      "Colour":2,
      "ValueDisplayMode":0
    },
    {
      "Name":"3",
      "ID":1581218762,
      "Position":{
        "x":-30.51437,
        "y":1.07712
      },
      "BitCount":1,
      "Colour":3,
      "ValueDisplayMode":0
    },
    {
      "Name":"4",
      "ID":2006692227,
      "Position":{
        "x":-30.49767,
        "y":-0.02695
      },
      "BitCount":1,
      "Colour":4,
      "ValueDisplayMode":0
    },
    {
      "Name":"5",
      "ID":890359588,
      "Position":{
        "x":-30.49767,
        "y":-1.15195
      },
      "BitCount":1,
      "Colour":5,
      "ValueDisplayMode":0
    },
    {
      "Name":"6",
      "ID":1598628106,
      "Position":{
        "x":-30.49767,
        "y":-2.27695
      },
      "BitCount":1,
      "Colour":0,
      "ValueDisplayMode":0
    },
    {
      "Name":"7",
      "ID":443535635,
      "Position":{
        "x":-30.49767,
        "y":-3.40195
      },
      "BitCount":1,
      "Colour":6,
      "ValueDisplayMode":0
    }
  ],
  "OutputPins":[
    {
      "Name":"OUT",
      "ID":1447308346,
      "Position":{
        "x":-7.875,
        "y":0.25
      },
      "BitCount":1,
      "Colour":0,
      "ValueDisplayMode":0
    }
  ],
  "SubChips":[
    {
      "Name":"AND-4",
      "ID":1476995567,
      "Label":"",
      "Position":{
        "x":-14.19187,
        "y":4.07712
      },
      "OutputPinColourInfo":[{"PinColour":0,"PinID":361196553}],
      "InternalData":null
    },
    {
      "Name":"AND-4",
      "ID":1171251844,
      "Label":"",
      "Position":{
        "x":-14.19187,
        "y":2.95212
      },
      "OutputPinColourInfo":[{"PinColour":0,"PinID":361196553}],
      "InternalData":null
    },
    {
      "Name":"AND-4",
      "ID":707412721,
      "Label":"",
      "Position":{
        "x":-14.19187,
        "y":1.82712
      },
      "OutputPinColourInfo":[{"PinColour":0,"PinID":361196553}],
      "InternalData":null
    },
    {
      "Name":"AND-4",
      "ID":2143599168,
      "Label":"",
      "Position":{
        "x":-14.19187,
        "y":0.70212
      },
      "OutputPinColourInfo":[{"PinColour":0,"PinID":361196553}],
      "InternalData":null
    },
    {
      "Name":"AND-4",
      "ID":1587463316,
      "Label":"",
      "Position":{
        "x":-14.19221,
        "y":-0.43552
      },
      "OutputPinColourInfo":[{"PinColour":0,"PinID":361196553}],
      "InternalData":null
    },
    {
      "Name":"BUS-1",
      "ID":908450413,
      "Label":"C1",
      "Position":{
        "x":-25.00437,
        "y":8.82712
      },
      "OutputPinColourInfo":null,
      "InternalData":[901635480,0]
    },
    {
      "Name":"BUS-TERMINUS-1",
      "ID":901635480,
      "Label":"",
      "Position":{
        "x":-24.75437,
        "y":-4.66012
      },
      "OutputPinColourInfo":null,
      "InternalData":[908450413,0]
    },
    {
      "Name":"BUS-1",
      "ID":708551224,
      "Label":"~C1",
      "Position":{
        "x":-23.62937,
        "y":8.82712
      },
      "OutputPinColourInfo":null,
      "InternalData":[3108915,0]
    },
    {
      "Name":"BUS-TERMINUS-1",
      "ID":3108915,
      "Label":"",
      "Position":{
        "x":-23.37937,
        "y":-4.66012
      },
      "OutputPinColourInfo":null,
      "InternalData":[708551224,0]
    },
    {
      "Name":"BUS-1",
      "ID":2129378221,
      "Label":"C2",
      "Position":{
        "x":-21.37937,
        "y":8.82712
      },
      "OutputPinColourInfo":null,
      "InternalData":[194863731,0]
    },
    {
      "Name":"BUS-TERMINUS-1",
      "ID":194863731,
      "Label":"",
      "Position":{
        "x":-21.12937,
        "y":-4.66012
      },
      "OutputPinColourInfo":null,
      "InternalData":[2129378221,0]
    },
    {
      "Name":"BUS-1",
      "ID":2060053131,
      "Label":"~C2",
      "Position":{
        "x":-19.87937,
        "y":8.82712
      },
      "OutputPinColourInfo":null,
      "InternalData":[1059549994,0]
    },
    {
      "Name":"BUS-TERMINUS-1",
      "ID":1059549994,
      "Label":"",
      "Position":{
        "x":-19.62937,
        "y":-4.66012
      },
      "OutputPinColourInfo":null,
      "InternalData":[2060053131,0]
    },
    {
      "Name":"BUS-1",
      "ID":738631658,
      "Label":"C3",
      "Position":{
        "x":-17.75437,
        "y":8.82712
      },
      "OutputPinColourInfo":null,
      "InternalData":[592617256,0]
    },
    {
      "Name":"BUS-TERMINUS-1",
      "ID":592617256,
      "Label":"",
      "Position":{
        "x":-17.50437,
        "y":-4.66036
      },
      "OutputPinColourInfo":null,
      "InternalData":[738631658,0]
    },
    {
      "Name":"BUS-1",
      "ID":1757213221,
      "Label":"~C3",
      "Position":{
        "x":-16.37937,
        "y":8.82712
      },
      "OutputPinColourInfo":null,
      "InternalData":[12353082,0]
    },
    {
      "Name":"BUS-TERMINUS-1",
      "ID":12353082,
      "Label":"",
      "Position":{
        "x":-16.12937,
        "y":-4.66012
      },
      "OutputPinColourInfo":null,
      "InternalData":[1757213221,0]
    },
    {
      "Name":"NOT",
      "ID":533388601,
      "Label":"",
      "Position":{
        "x":-24.21686,
        "y":8.01462
      },
      "OutputPinColourInfo":[{"PinColour":0,"PinID":1489444864}],
      "InternalData":null
    },
    {
      "Name":"NOT",
      "ID":112926924,
      "Label":"",
      "Position":{
        "x":-20.46687,
        "y":6.76462
      },
      "OutputPinColourInfo":[{"PinColour":0,"PinID":1489444864}],
      "InternalData":null
    },
    {
      "Name":"NOT",
      "ID":1592804619,
      "Label":"",
      "Position":{
        "x":-16.96687,
        "y":5.32712
      },
      "OutputPinColourInfo":[{"PinColour":0,"PinID":1489444864}],
      "InternalData":null
    },
    {
      "Name":"AND-4",
      "ID":720452758,
      "Label":"",
      "Position":{
        "x":-14.19221,
        "y":-1.56052
      },
      "OutputPinColourInfo":[{"PinColour":0,"PinID":361196553}],
      "InternalData":null
    },
    {
      "Name":"AND-4",
      "ID":1735153033,
      "Label":"",
      "Position":{
        "x":-14.19221,
        "y":-2.68552
      },
      "OutputPinColourInfo":[{"PinColour":0,"PinID":361196553}],
      "InternalData":null
    },
    {
      "Name":"AND-4",
      "ID":1977016277,
      "Label":"",
      "Position":{
        "x":-14.19221,
        "y":-3.81052
      },
      "OutputPinColourInfo":[{"PinColour":0,"PinID":361196553}],
      "InternalData":null
    },
    {
      "Name":"OR-8",
      "ID":767332384,
      "Label":"",
      "Position":{
        "x":-10.2525,
        "y":0.25
      },
      "OutputPinColourInfo":[{"PinColour":0,"PinID":1846824642}],
      "InternalData":null
    }
  ],
  "Wires":[
    {
      "SourcePinAddress":{
        "PinID":1,
        "PinOwnerID":908450413
      },
      "TargetPinAddress":{
        "PinID":0,
        "PinOwnerID":901635480
      },
      "ConnectionType":0,
      "ConnectedWireIndex":-1,
      "ConnectedWireSegmentIndex":-1,
      "Points":[{"x":0.0,"y":0.0},{"x":0.0,"y":0.0}]
    },
    {
      "SourcePinAddress":{
        "PinID":1,
        "PinOwnerID":708551224
      },
      "TargetPinAddress":{
        "PinID":0,
        "PinOwnerID":3108915
      },
      "ConnectionType":0,
      "ConnectedWireIndex":-1,
      "ConnectedWireSegmentIndex":-1,
      "Points":[{"x":0.0,"y":0.0},{"x":0.0,"y":0.0}]
    },
    {
      "SourcePinAddress":{
        "PinID":1,
        "PinOwnerID":2129378221
      },
      "TargetPinAddress":{
        "PinID":0,
        "PinOwnerID":194863731
      },
      "ConnectionType":0,
      "ConnectedWireIndex":-1,
      "ConnectedWireSegmentIndex":-1,
      "Points":[{"x":0.0,"y":0.0},{"x":0.0,"y":0.0}]
    },
    {
      "SourcePinAddress":{
        "PinID":1,
        "PinOwnerID":2060053131
      },
      "TargetPinAddress":{
        "PinID":0,
        "PinOwnerID":1059549994
      },
      "ConnectionType":0,
      "ConnectedWireIndex":-1,
      "ConnectedWireSegmentIndex":-1,
      "Points":[{"x":0.0,"y":0.0},{"x":0.0,"y":0.0}]
    },
    {
      "SourcePinAddress":{
        "PinID":1,
        "PinOwnerID":738631658
      },
      "TargetPinAddress":{
        "PinID":0,
        "PinOwnerID":592617256
      },
      "ConnectionType":0,
      "ConnectedWireIndex":-1,
      "ConnectedWireSegmentIndex":-1,
      "Points":[{"x":0.0,"y":0.0},{"x":0.0,"y":0.0}]
    },
    {
      "SourcePinAddress":{
        "PinID":1,
        "PinOwnerID":1757213221
      },
      "TargetPinAddress":{
        "PinID":0,
        "PinOwnerID":12353082
      },
      "ConnectionType":0,
      "ConnectedWireIndex":-1,
      "ConnectedWireSegmentIndex":-1,
      "Points":[{"x":0.0,"y":0.0},{"x":0.0,"y":0.0}]
    },
    {
      "SourcePinAddress":{
        "PinID":0,
        "PinOwnerID":1584892759
      },
      "TargetPinAddress":{
        "PinID":1972367813,
        "PinOwnerID":533388601
      },
      "ConnectionType":0,
      "ConnectedWireIndex":-1,
      "ConnectedWireSegmentIndex":-1,
      "Points":[{"x":0.0,"y":0.0},{"x":0.0,"y":0.0}]
    },
    {
      "SourcePinAddress":{
        "PinID":1489444864,
        "PinOwnerID":533388601
      },
      "TargetPinAddress":{
        "PinID":0,
        "PinOwnerID":708551224
      },
      "ConnectionType":2,
      "ConnectedWireIndex":1,
      "ConnectedWireSegmentIndex":0,
      "Points":[{"x":0.0,"y":0.0},{"x":-23.49559,"y":8.00544}]
    },
    {
      "SourcePinAddress":{
        "PinID":0,
        "PinOwnerID":1584892759
      },
      "TargetPinAddress":{
        "PinID":0,
        "PinOwnerID":908450413
      },
      "ConnectionType":2,
      "ConnectedWireIndex":0,
      "ConnectedWireSegmentIndex":0,
      "Points":[{"x":0.0,"y":0.0},{"x":-27.62564,"y":8.56181},{"x":-24.86976,"y":8.56172}]
    },
    {
      "SourcePinAddress":{
        "PinID":0,
        "PinOwnerID":2138233393
      },
      "TargetPinAddress":{
        "PinID":1972367813,
        "PinOwnerID":112926924
      },
      "ConnectionType":0,
      "ConnectedWireIndex":-1,
      "ConnectedWireSegmentIndex":-1,
      "Points":[{"x":0.0,"y":0.0},{"x":0.0,"y":0.0}]
    },
    {
      "SourcePinAddress":{
        "PinID":1489444864,
        "PinOwnerID":112926924
      },
      "TargetPinAddress":{
        "PinID":0,
        "PinOwnerID":2060053131
      },
      "ConnectionType":2,
      "ConnectedWireIndex":3,
      "ConnectedWireSegmentIndex":0,
      "Points":[{"x":0.0,"y":0.0},{"x":-19.74743,"y":6.76491}]
    },
    {
      "SourcePinAddress":{
        "PinID":0,
        "PinOwnerID":2138233393
      },
      "TargetPinAddress":{
        "PinID":0,
        "PinOwnerID":2129378221
      },
      "ConnectionType":2,
      "ConnectedWireIndex":2,
      "ConnectedWireSegmentIndex":0,
      "Points":[{"x":0.0,"y":0.0},{"x":-27.66239,"y":7.26842},{"x":-21.24668,"y":7.26859}]
    },
    {
      "SourcePinAddress":{
        "PinID":0,
        "PinOwnerID":509777400
      },
      "TargetPinAddress":{
        "PinID":1972367813,
        "PinOwnerID":1592804619
      },
      "ConnectionType":0,
      "ConnectedWireIndex":-1,
      "ConnectedWireSegmentIndex":-1,
      "Points":[{"x":0.0,"y":0.0},{"x":0.0,"y":0.0}]
    },
    {
      "SourcePinAddress":{
        "PinID":0,
        "PinOwnerID":509777400
      },
      "TargetPinAddress":{
        "PinID":0,
        "PinOwnerID":738631658
      },
      "ConnectionType":2,
      "ConnectedWireIndex":4,
      "ConnectedWireSegmentIndex":0,
      "Points":[{"x":0.0,"y":0.0},{"x":-27.67086,"y":6.06611},{"x":-17.62346,"y":6.06612}]
    },
    {
      "SourcePinAddress":{
        "PinID":1489444864,
        "PinOwnerID":1592804619
      },
      "TargetPinAddress":{
        "PinID":0,
        "PinOwnerID":1757213221
      },
      "ConnectionType":2,
      "ConnectedWireIndex":5,
      "ConnectedWireSegmentIndex":0,
      "Points":[{"x":0.0,"y":0.0},{"x":-16.24955,"y":5.33539}]
    },
    {
      "SourcePinAddress":{
        "PinID":0,
        "PinOwnerID":1967958892
      },
      "TargetPinAddress":{
        "PinID":1690467366,
        "PinOwnerID":1476995567
      },
      "ConnectionType":0,
      "ConnectedWireIndex":-1,
      "ConnectedWireSegmentIndex":-1,
      "Points":[{"x":0.0,"y":0.0},{"x":0.0,"y":0.0}]
    },
    {
      "SourcePinAddress":{
        "PinID":0,
        "PinOwnerID":1672132232
      },
      "TargetPinAddress":{
        "PinID":1690467366,
        "PinOwnerID":1171251844
      },
      "ConnectionType":0,
      "ConnectedWireIndex":-1,
      "ConnectedWireSegmentIndex":-1,
      "Points":[{"x":0.0,"y":0.0},{"x":0.0,"y":0.0}]
    },
    {
      "SourcePinAddress":{
        "PinID":0,
        "PinOwnerID":1176604405
      },
      "TargetPinAddress":{
        "PinID":1690467366,
        "PinOwnerID":707412721
      },
      "ConnectionType":0,
      "ConnectedWireIndex":-1,
      "ConnectedWireSegmentIndex":-1,
      "Points":[{"x":0.0,"y":0.0},{"x":0.0,"y":0.0}]
    },
    {
      "SourcePinAddress":{
        "PinID":0,
        "PinOwnerID":1581218762
      },
      "TargetPinAddress":{
        "PinID":1690467366,
        "PinOwnerID":2143599168
      },
      "ConnectionType":0,
      "ConnectedWireIndex":-1,
      "ConnectedWireSegmentIndex":-1,
      "Points":[{"x":0.0,"y":0.0},{"x":0.0,"y":0.0}]
    },
    {
      "SourcePinAddress":{
        "PinID":0,
        "PinOwnerID":2006692227
      },
      "TargetPinAddress":{
        "PinID":1690467366,
        "PinOwnerID":1587463316
      },
      "ConnectionType":0,
      "ConnectedWireIndex":-1,
      "ConnectedWireSegmentIndex":-1,
      "Points":[{"x":0.0,"y":0.0},{"x":0.0,"y":0.0}]
    },
    {
      "SourcePinAddress":{
        "PinID":0,
        "PinOwnerID":890359588
      },
      "TargetPinAddress":{
        "PinID":1690467366,
        "PinOwnerID":720452758
      },
      "ConnectionType":0,
      "ConnectedWireIndex":-1,
      "ConnectedWireSegmentIndex":-1,
      "Points":[{"x":0.0,"y":0.0},{"x":0.0,"y":0.0}]
    },
    {
      "SourcePinAddress":{
        "PinID":0,
        "PinOwnerID":1598628106
      },
      "TargetPinAddress":{
        "PinID":1690467366,
        "PinOwnerID":1735153033
      },
      "ConnectionType":0,
      "ConnectedWireIndex":-1,
      "ConnectedWireSegmentIndex":-1,
      "Points":[{"x":0.0,"y":0.0},{"x":0.0,"y":0.0}]
    },
    {
      "SourcePinAddress":{
        "PinID":0,
        "PinOwnerID":443535635
      },
      "TargetPinAddress":{
        "PinID":1690467366,
        "PinOwnerID":1977016277
      },
      "ConnectionType":0,
      "ConnectedWireIndex":-1,
      "ConnectedWireSegmentIndex":-1,
      "Points":[{"x":0.0,"y":0.0},{"x":0.0,"y":0.0}]
    },
    {
      "SourcePinAddress":{
        "PinID":1,
        "PinOwnerID":1757213221
      },
      "TargetPinAddress":{
        "PinID":858977689,
        "PinOwnerID":1476995567
      },
      "ConnectionType":1,
      "ConnectedWireIndex":5,
      "ConnectedWireSegmentIndex":0,
      "Points":[{"x":-16.25197,"y":3.70209},{"x":0.0,"y":0.0}]
    },
    {
      "SourcePinAddress":{
        "PinID":1,
        "PinOwnerID":2060053131
      },
      "TargetPinAddress":{
        "PinID":133624384,
        "PinOwnerID":1476995567
      },
      "ConnectionType":1,
      "ConnectedWireIndex":3,
      "ConnectedWireSegmentIndex":0,
      "Points":[{"x":-19.7516,"y":3.95214},{"x":0.0,"y":0.0}]
    },
    {
      "SourcePinAddress":{
        "PinID":1,
        "PinOwnerID":708551224
      },
      "TargetPinAddress":{
        "PinID":2090819378,
        "PinOwnerID":1476995567
      },
      "ConnectionType":1,
      "ConnectedWireIndex":1,
      "ConnectedWireSegmentIndex":0,
      "Points":[{"x":-23.50123,"y":4.20213},{"x":0.0,"y":0.0}]
    },
    {
      "SourcePinAddress":{
        "PinID":1,
        "PinOwnerID":908450413
      },
      "TargetPinAddress":{
        "PinID":2090819378,
        "PinOwnerID":1171251844
      },
      "ConnectionType":1,
      "ConnectedWireIndex":0,
      "ConnectedWireSegmentIndex":0,
      "Points":[{"x":-24.8779,"y":3.07711},{"x":0.0,"y":0.0}]
    },
    {
      "SourcePinAddress":{
        "PinID":1,
        "PinOwnerID":2060053131
      },
      "TargetPinAddress":{
        "PinID":133624384,
        "PinOwnerID":1171251844
      },
      "ConnectionType":1,
      "ConnectedWireIndex":3,
      "ConnectedWireSegmentIndex":0,
      "Points":[{"x":-19.75327,"y":2.82708},{"x":0.0,"y":0.0}]
    },
    {
      "SourcePinAddress":{
        "PinID":1,
        "PinOwnerID":1757213221
      },
      "TargetPinAddress":{
        "PinID":858977689,
        "PinOwnerID":1171251844
      },
      "ConnectionType":1,
      "ConnectedWireIndex":5,
      "ConnectedWireSegmentIndex":0,
      "Points":[{"x":-16.25364,"y":2.57712},{"x":0.0,"y":0.0}]
    },
    {
      "SourcePinAddress":{
        "PinID":1,
        "PinOwnerID":708551224
      },
      "TargetPinAddress":{
        "PinID":2090819378,
        "PinOwnerID":707412721
      },
      "ConnectionType":1,
      "ConnectedWireIndex":1,
      "ConnectedWireSegmentIndex":0,
      "Points":[{"x":-23.50456,"y":1.9521},{"x":0.0,"y":0.0}]
    },
    {
      "SourcePinAddress":{
        "PinID":1,
        "PinOwnerID":2129378221
      },
      "TargetPinAddress":{
        "PinID":133624384,
        "PinOwnerID":707412721
      },
      "ConnectionType":1,
      "ConnectedWireIndex":2,
      "ConnectedWireSegmentIndex":0,
      "Points":[{"x":-21.25493,"y":1.70216},{"x":0.0,"y":0.0}]
    },
    {
      "SourcePinAddress":{
        "PinID":1,
        "PinOwnerID":1757213221
      },
      "TargetPinAddress":{
        "PinID":858977689,
        "PinOwnerID":707412721
      },
      "ConnectionType":1,
      "ConnectedWireIndex":5,
      "ConnectedWireSegmentIndex":0,
      "Points":[{"x":-16.25531,"y":1.45213},{"x":0.0,"y":0.0}]
    },
    {
      "SourcePinAddress":{
        "PinID":1,
        "PinOwnerID":908450413
      },
      "TargetPinAddress":{
        "PinID":2090819378,
        "PinOwnerID":2143599168
      },
      "ConnectionType":1,
      "ConnectedWireIndex":0,
      "ConnectedWireSegmentIndex":0,
      "Points":[{"x":-24.88123,"y":0.82713},{"x":0.0,"y":0.0}]
    },
    {
      "SourcePinAddress":{
        "PinID":1,
        "PinOwnerID":2129378221
      },
      "TargetPinAddress":{
        "PinID":133624384,
        "PinOwnerID":2143599168
      },
      "ConnectionType":1,
      "ConnectedWireIndex":2,
      "ConnectedWireSegmentIndex":0,
      "Points":[{"x":-21.2566,"y":0.57716},{"x":0.0,"y":0.0}]
    },
    {
      "SourcePinAddress":{
        "PinID":1,
        "PinOwnerID":1757213221
      },
      "TargetPinAddress":{
        "PinID":858977689,
        "PinOwnerID":2143599168
      },
      "ConnectionType":1,
      "ConnectedWireIndex":5,
      "ConnectedWireSegmentIndex":0,
      "Points":[{"x":-16.25698,"y":0.32716},{"x":0.0,"y":0.0}]
    },
    {
      "SourcePinAddress":{
        "PinID":1,
        "PinOwnerID":708551224
      },
      "TargetPinAddress":{
        "PinID":2090819378,
        "PinOwnerID":1587463316
      },
      "ConnectionType":1,
      "ConnectedWireIndex":1,
      "ConnectedWireSegmentIndex":0,
      "Points":[{"x":-23.50792,"y":-0.31056},{"x":0.0,"y":0.0}]
    },
    {
      "SourcePinAddress":{
        "PinID":1,
        "PinOwnerID":2060053131
      },
      "TargetPinAddress":{
        "PinID":133624384,
        "PinOwnerID":1587463316
      },
      "ConnectionType":1,
      "ConnectedWireIndex":3,
      "ConnectedWireSegmentIndex":0,
      "Points":[{"x":-19.75829,"y":-0.56049},{"x":0.0,"y":0.0}]
    },
    {
      "SourcePinAddress":{
        "PinID":1,
        "PinOwnerID":738631658
      },
      "TargetPinAddress":{
        "PinID":858977689,
        "PinOwnerID":1587463316
      },
      "ConnectionType":1,
      "ConnectedWireIndex":4,
      "ConnectedWireSegmentIndex":0,
      "Points":[{"x":-17.63366,"y":-0.8105},{"x":0.0,"y":0.0}]
    },
    {
      "SourcePinAddress":{
        "PinID":1,
        "PinOwnerID":908450413
      },
      "TargetPinAddress":{
        "PinID":2090819378,
        "PinOwnerID":720452758
      },
      "ConnectionType":1,
      "ConnectedWireIndex":0,
      "ConnectedWireSegmentIndex":0,
      "Points":[{"x":-24.88459,"y":-1.4355},{"x":0.0,"y":0.0}]
    },
    {
      "SourcePinAddress":{
        "PinID":1,
        "PinOwnerID":2060053131
      },
      "TargetPinAddress":{
        "PinID":133624384,
        "PinOwnerID":720452758
      },
      "ConnectionType":1,
      "ConnectedWireIndex":3,
      "ConnectedWireSegmentIndex":0,
      "Points":[{"x":-19.75996,"y":-1.68549},{"x":0.0,"y":0.0}]
    },
    {
      "SourcePinAddress":{
        "PinID":1,
        "PinOwnerID":738631658
      },
      "TargetPinAddress":{
        "PinID":858977689,
        "PinOwnerID":720452758
      },
      "ConnectionType":1,
      "ConnectedWireIndex":4,
      "ConnectedWireSegmentIndex":0,
      "Points":[{"x":-17.63533,"y":-1.9355},{"x":0.0,"y":0.0}]
    },
    {
      "SourcePinAddress":{
        "PinID":1,
        "PinOwnerID":708551224
      },
      "TargetPinAddress":{
        "PinID":2090819378,
        "PinOwnerID":1735153033
      },
      "ConnectionType":1,
      "ConnectedWireIndex":1,
      "ConnectedWireSegmentIndex":0,
      "Points":[{"x":-23.51126,"y":-2.56048},{"x":0.0,"y":0.0}]
    },
    {
      "SourcePinAddress":{
        "PinID":1,
        "PinOwnerID":2129378221
      },
      "TargetPinAddress":{
        "PinID":133624384,
        "PinOwnerID":1735153033
      },
      "ConnectionType":1,
      "ConnectedWireIndex":2,
      "ConnectedWireSegmentIndex":0,
      "Points":[{"x":-21.26163,"y":-2.8105},{"x":0.0,"y":0.0}]
    },
    {
      "SourcePinAddress":{
        "PinID":1,
        "PinOwnerID":738631658
      },
      "TargetPinAddress":{
        "PinID":858977689,
        "PinOwnerID":1735153033
      },
      "ConnectionType":1,
      "ConnectedWireIndex":4,
      "ConnectedWireSegmentIndex":0,
      "Points":[{"x":-17.637,"y":-3.06047},{"x":0.0,"y":0.0}]
    },
    {
      "SourcePinAddress":{
        "PinID":1,
        "PinOwnerID":908450413
      },
      "TargetPinAddress":{
        "PinID":2090819378,
        "PinOwnerID":1977016277
      },
      "ConnectionType":1,
      "ConnectedWireIndex":0,
      "ConnectedWireSegmentIndex":0,
      "Points":[{"x":-24.88792,"y":-3.68548},{"x":0.0,"y":0.0}]
    },
    {
      "SourcePinAddress":{
        "PinID":1,
        "PinOwnerID":2129378221
      },
      "TargetPinAddress":{
        "PinID":133624384,
        "PinOwnerID":1977016277
      },
      "ConnectionType":1,
      "ConnectedWireIndex":2,
      "ConnectedWireSegmentIndex":0,
      "Points":[{"x":-21.2633,"y":-3.9355},{"x":0.0,"y":0.0}]
    },
    {
      "SourcePinAddress":{
        "PinID":1,
        "PinOwnerID":738631658
      },
      "TargetPinAddress":{
        "PinID":858977689,
        "PinOwnerID":1977016277
      },
      "ConnectionType":1,
      "ConnectedWireIndex":4,
      "ConnectedWireSegmentIndex":0,
      "Points":[{"x":-17.63867,"y":-4.18547},{"x":0.0,"y":0.0}]
    },
    {
      "SourcePinAddress":{
        "PinID":361196553,
        "PinOwnerID":1476995567
      },
      "TargetPinAddress":{
        "PinID":1683282859,
        "PinOwnerID":767332384
      },
      "ConnectionType":0,
      "ConnectedWireIndex":-1,
      "ConnectedWireSegmentIndex":-1,
      "Points":[{"x":0.0,"y":0.0},{"x":0.0,"y":0.0}]
    },
    {
      "SourcePinAddress":{
        "PinID":361196553,
        "PinOwnerID":1171251844
      },
      "TargetPinAddress":{
        "PinID":1008543163,
        "PinOwnerID":767332384
      },
      "ConnectionType":0,
      "ConnectedWireIndex":-1,
      "ConnectedWireSegmentIndex":-1,
      "Points":[{"x":0.0,"y":0.0},{"x":0.0,"y":0.0}]
    },
    {
      "SourcePinAddress":{
        "PinID":361196553,
        "PinOwnerID":707412721
      },
      "TargetPinAddress":{
        "PinID":1116068652,
        "PinOwnerID":767332384
      },
      "ConnectionType":0,
      "ConnectedWireIndex":-1,
      "ConnectedWireSegmentIndex":-1,
      "Points":[{"x":0.0,"y":0.0},{"x":0.0,"y":0.0}]
    },
    {
      "SourcePinAddress":{
        "PinID":361196553,
        "PinOwnerID":2143599168
      },
      "TargetPinAddress":{
        "PinID":1741543516,
        "PinOwnerID":767332384
      },
      "ConnectionType":0,
      "ConnectedWireIndex":-1,
      "ConnectedWireSegmentIndex":-1,
      "Points":[{"x":0.0,"y":0.0},{"x":0.0,"y":0.0}]
    },
    {
      "SourcePinAddress":{
        "PinID":361196553,
        "PinOwnerID":1587463316
      },
      "TargetPinAddress":{
        "PinID":635873563,
        "PinOwnerID":767332384
      },
      "ConnectionType":0,
      "ConnectedWireIndex":-1,
      "ConnectedWireSegmentIndex":-1,
      "Points":[{"x":0.0,"y":0.0},{"x":0.0,"y":0.0}]
    },
    {
      "SourcePinAddress":{
        "PinID":361196553,
        "PinOwnerID":720452758
      },
      "TargetPinAddress":{
        "PinID":1411080670,
        "PinOwnerID":767332384
      },
      "ConnectionType":0,
      "ConnectedWireIndex":-1,
      "ConnectedWireSegmentIndex":-1,
      "Points":[{"x":0.0,"y":0.0},{"x":0.0,"y":0.0}]
    },
    {
      "SourcePinAddress":{
        "PinID":361196553,
        "PinOwnerID":1735153033
      },
      "TargetPinAddress":{
        "PinID":887190075,
        "PinOwnerID":767332384
      },
      "ConnectionType":0,
      "ConnectedWireIndex":-1,
      "ConnectedWireSegmentIndex":-1,
      "Points":[{"x":0.0,"y":0.0},{"x":0.0,"y":0.0}]
    },
    {
      "SourcePinAddress":{
        "PinID":361196553,
        "PinOwnerID":1977016277
      },
      "TargetPinAddress":{
        "PinID":238054960,
        "PinOwnerID":767332384
      },
      "ConnectionType":0,
      "ConnectedWireIndex":-1,
      "ConnectedWireSegmentIndex":-1,
      "Points":[{"x":0.0,"y":0.0},{"x":0.0,"y":0.0}]
    },
    {
      "SourcePinAddress":{
        "PinID":1846824642,
        "PinOwnerID":767332384
      },
      "TargetPinAddress":{
        "PinID":0,
        "PinOwnerID":1447308346
      },
      "ConnectionType":0,
      "ConnectedWireIndex":-1,
      "ConnectedWireSegmentIndex":-1,
      "Points":[{"x":0.0,"y":0.0},{"x":0.0,"y":0.0}]
    }
  ],
  "Displays":[]
}